aionetworking/__init__.py
aionetworking/__version__.py
aionetworking/compatibility.py
aionetworking/compatibility_os.py
aionetworking/factories.py
aionetworking/runners.py
aionetworking/settings.py
aionetworking/utils.py
aionetworking/actions/__init__.py
aionetworking/actions/base.py
aionetworking/actions/echo.py
aionetworking/actions/file_storage.py
aionetworking/actions/protocols.py
aionetworking/actions/yaml_constructors.py
aionetworking/conf/__init__.py
aionetworking/conf/windows_service.py
aionetworking/conf/yaml_config.py
aionetworking/conf/yaml_constructors.py
aionetworking/formats/__init__.py
aionetworking/formats/base.py
aionetworking/formats/protocols.py
aionetworking/formats/recording.py
aionetworking/formats/contrib/__init__.py
aionetworking/formats/contrib/json.py
aionetworking/formats/contrib/pickle.py
aionetworking/formats/contrib/yaml_constructors.py
aionetworking/futures/__init__.py
aionetworking/futures/counters.py
aionetworking/futures/schedulers.py
aionetworking/futures/value_waiters.py
aionetworking/logging/__init__.py
aionetworking/logging/log_filters.py
aionetworking/logging/loggers.py
aionetworking/logging/utils_logging.py
aionetworking/networking/__init__.py
aionetworking/networking/adaptors.py
aionetworking/networking/connections.py
aionetworking/networking/connections_manager.py
aionetworking/networking/exceptions.py
aionetworking/networking/protocol_factories.py
aionetworking/networking/protocols.py
aionetworking/networking/sftp.py
aionetworking/networking/sftp_os_auth.py
aionetworking/networking/ssl.py
aionetworking/networking/ssl_utils.py
aionetworking/networking/transports.py
aionetworking/networking/yaml_constructors.py
aionetworking/networking/yaml_constructors_sftp.py
aionetworking/receivers/__init__.py
aionetworking/receivers/base.py
aionetworking/receivers/cli_tool.py
aionetworking/receivers/exceptions.py
aionetworking/receivers/protocols.py
aionetworking/receivers/servers.py
aionetworking/receivers/sftp.py
aionetworking-2.1.0.dist-info/licenses/LICENSE.txt
aionetworking-2.1.0.dist-info/METADATA
aionetworking-2.1.0.dist-info/WHEEL
aionetworking-2.1.0.dist-info/top_level.txt
aionetworking-2.1.0.dist-info/RECORD
